{
  "provedor": "Titan Terminal Data Engine",
  "status": "success",
  "ultima_atualizacao": "2026-06-06T22:44:53.443Z",
  "mercado": {
    "beam": {
      "usd": 0.01551911,
      "brl": 0.080352
    },
    "bytecoin": {
      "usd": 0.00004303,
      "brl": 0.00022278
    },
    "dash": {
      "usd": 31.76,
      "brl": 164.43
    },
    "decred": {
      "usd": 12.25,
      "brl": 63.41
    },
    "epic-cash": {
      "usd": 0.173219,
      "brl": 0.896858
    },
    "grin": {
      "usd": 0.02736801,
      "brl": 0.141701
    },
    "karbo": {
      "usd": 0.03382962,
      "brl": 0.171252
    },
    "monero": {
      "usd": 293.73,
      "brl": 1520.82
    },
    "oasis-network": {
      "usd": 0.00638847,
      "brl": 0.03307693
    },
    "pirate-chain": {
      "usd": 0.331253,
      "brl": 1.72
    },
    "secret": {
      "usd": 0.05912,
      "brl": 0.306101
    },
    "ycash": {
      "usd": 0.261566,
      "brl": 1.35
    },
    "zcash": {
      "usd": 350.15,
      "brl": 1812.96
    },
    "zclassic": {
      "usd": 0.184499,
      "brl": 0.955262
    }
  }
}