{
  "provedor": "Titan Terminal Data Engine",
  "status": "success",
  "ultima_atualizacao": "2026-07-01T04:56:22.473Z",
  "mercado": {
    "beam": {
      "usd": 0.00702404,
      "brl": 0.03636067
    },
    "bytecoin": {
      "usd": 0.00003404,
      "brl": 0.00017663
    },
    "dash": {
      "usd": 33.2,
      "brl": 171.85
    },
    "decred": {
      "usd": 10.85,
      "brl": 56.16
    },
    "epic-cash": {
      "usd": 0.207141,
      "brl": 1.072
    },
    "grin": {
      "usd": 0.01794281,
      "brl": 0.092883
    },
    "karbo": {
      "usd": 0.02583596,
      "brl": 0.1339
    },
    "monero": {
      "usd": 308.76,
      "brl": 1598.3
    },
    "oasis-network": {
      "usd": 0.00570622,
      "brl": 0.02953883
    },
    "pirate-chain": {
      "usd": 0.23635,
      "brl": 1.22
    },
    "secret": {
      "usd": 0.0484878,
      "brl": 0.251002
    },
    "ycash": {
      "usd": 0.167933,
      "brl": 0.869321
    },
    "zcash": {
      "usd": 408.71,
      "brl": 2115.72
    },
    "zclassic": {
      "usd": 0.179824,
      "brl": 0.930878
    }
  }
}