{
  "provedor": "Titan Terminal Data Engine",
  "status": "success",
  "ultima_atualizacao": "2026-06-27T09:51:54.051Z",
  "mercado": {
    "beam": {
      "usd": 0.00895044,
      "brl": 0.04641787
    },
    "bytecoin": {
      "usd": 0.00003405,
      "brl": 0.00017658
    },
    "dash": {
      "usd": 33.73,
      "brl": 174.9
    },
    "decred": {
      "usd": 11.17,
      "brl": 57.92
    },
    "epic-cash": {
      "usd": 0.194857,
      "brl": 1.011
    },
    "grin": {
      "usd": 0.02329341,
      "brl": 0.120802
    },
    "karbo": {
      "usd": 0.03118649,
      "brl": 0.162444
    },
    "monero": {
      "usd": 314.51,
      "brl": 1631.07
    },
    "oasis-network": {
      "usd": 0.00589851,
      "brl": 0.03059024
    },
    "pirate-chain": {
      "usd": 0.251711,
      "brl": 1.31
    },
    "secret": {
      "usd": 0.050815,
      "brl": 0.26353
    },
    "ycash": {
      "usd": 0.143754,
      "brl": 0.745523
    },
    "zcash": {
      "usd": 408.07,
      "brl": 2116.28
    },
    "zclassic": {
      "usd": 0.180215,
      "brl": 0.934615
    }
  }
}