{
  "provedor": "Titan Terminal Data Engine",
  "status": "success",
  "ultima_atualizacao": "2026-06-15T20:05:35.911Z",
  "mercado": {
    "beam": {
      "usd": 0.01569121,
      "brl": 0.079757
    },
    "bytecoin": {
      "usd": 0.00003498,
      "brl": 0.0001778
    },
    "dash": {
      "usd": 38.78,
      "brl": 197.13
    },
    "decred": {
      "usd": 12.71,
      "brl": 64.58
    },
    "epic-cash": {
      "usd": 0.185691,
      "brl": 0.94385
    },
    "grin": {
      "usd": 0.02765492,
      "brl": 0.140567
    },
    "karbo": {
      "usd": 0.03338734,
      "brl": 0.169705
    },
    "monero": {
      "usd": 364.27,
      "brl": 1851.54
    },
    "oasis-network": {
      "usd": 0.00695465,
      "brl": 0.03534979
    },
    "pirate-chain": {
      "usd": 0.275674,
      "brl": 1.4
    },
    "secret": {
      "usd": 0.061238,
      "brl": 0.311269
    },
    "ycash": {
      "usd": 0.214265,
      "brl": 1.089
    },
    "zcash": {
      "usd": 523.8,
      "brl": 2662.4
    },
    "zclassic": {
      "usd": 0.146678,
      "brl": 0.745549
    }
  }
}