{
  "provedor": "Titan Terminal Data Engine",
  "status": "success",
  "ultima_atualizacao": "2026-07-06T17:29:23.941Z",
  "mercado": {
    "beam": {
      "usd": 0.00710788,
      "brl": 0.03661057
    },
    "bytecoin": {
      "usd": 0.00002498,
      "brl": 0.0001295
    },
    "dash": {
      "usd": 35.08,
      "brl": 180.71
    },
    "decred": {
      "usd": 11.25,
      "brl": 57.94
    },
    "epic-cash": {
      "usd": 0.208039,
      "brl": 1.072
    },
    "grin": {
      "usd": 0.02284883,
      "brl": 0.117687
    },
    "karbo": {
      "usd": 0.02581839,
      "brl": 0.133481
    },
    "monero": {
      "usd": 324.11,
      "brl": 1669.41
    },
    "oasis-network": {
      "usd": 0.00606879,
      "brl": 0.03125854
    },
    "pirate-chain": {
      "usd": 0.240059,
      "brl": 1.24
    },
    "secret": {
      "usd": 0.059762,
      "brl": 0.307814
    },
    "ycash": {
      "usd": 0.136787,
      "brl": 0.704551
    },
    "zcash": {
      "usd": 449.81,
      "brl": 2316.82
    },
    "zclassic": {
      "usd": 0.185134,
      "brl": 0.955108
    }
  }
}