{
  "provedor": "Titan Terminal Data Engine",
  "status": "success",
  "ultima_atualizacao": "2026-06-08T23:48:08.029Z",
  "mercado": {
    "beam": {
      "usd": 0.01561655,
      "brl": 0.081275
    },
    "bytecoin": {
      "usd": 0.00003499,
      "brl": 0.00018208
    },
    "dash": {
      "usd": 36.76,
      "brl": 191.33
    },
    "decred": {
      "usd": 12.27,
      "brl": 63.85
    },
    "epic-cash": {
      "usd": 0.189265,
      "brl": 0.985029
    },
    "grin": {
      "usd": 0.02672,
      "brl": 0.139062
    },
    "karbo": {
      "usd": 0.03382962,
      "brl": 0.171252
    },
    "monero": {
      "usd": 315.37,
      "brl": 1641.3
    },
    "oasis-network": {
      "usd": 0.00651163,
      "brl": 0.03388912
    },
    "pirate-chain": {
      "usd": 0.271022,
      "brl": 1.41
    },
    "secret": {
      "usd": 0.060642,
      "brl": 0.315604
    },
    "ycash": {
      "usd": 0.241984,
      "brl": 1.26
    },
    "zcash": {
      "usd": 457.44,
      "brl": 2380.72
    },
    "zclassic": {
      "usd": 0.182937,
      "brl": 0.952095
    }
  }
}